{
  "staging": [
    {"name": "REDBAR.NFT001", "id": "1.3.1635"},
    {"name": "REDBAR.NFT002", "id": "1.3.1636"},
    {"name": "REDBAR.NFT003", "id": "1.3.1637"},
    {"name": "REDBAR.NFT004", "id": "1.3.1662"},
    {"name": "REDBAR.NFT005", "id": "1.3.1663"},
    {"name": "REDBAR.NFT006", "id": "1.3.1664"},
    {"name": "REDBAR.NFT007", "id": "1.3.1665"},
    {"name": "REDBAR.NFT008", "id": "1.3.1666"},
    {"name": "REDBAR.NFT009", "id": "1.3.1667"},
    {"name": "REDBAR.NFT010", "id": "1.3.1668"},
    {"name": "MKUU.NFT00002", "id": "1.3.1628"},
    {"name": "MKUU.NFT00003", "id": "1.3.1629"},
    {"name": "MKUU.NFT00004", "id": "1.3.1630"},
    {"name": "MKUU.NFT00006", "id": "1.3.1634"},
    {"name": "MKUU.PASDEUX", "id": "1.3.1633"},
    {"name": "MKUU.TILES21", "id": "1.3.1638"},
    {"name": "NFTART.PIRATEDOG", "id": "1.3.1669"},
    {"name": "NFTART.3DFIRESW2", "id": "1.3.1672"},
    {"name": "NFTART.3DWOODAXE", "id": "1.3.1677"}
  ],
  "production": [
    {"name": "NFTEA.COPYB", "id": "1.3.6108"},
    {"name": "NFTEA.CHANCE", "id": "1.3.6107"},
    {"name": "NFTEA.CHANGE", "id": "1.3.6106"},
    {"name": "NFTEA.CONTROL", "id": "1.3.6105"},
    {"name": "NFTEA.CRIME", "id": "1.3.6104"},
    {"name": "NFTEA.CURRENT", "id": "1.3.6103"},
    {"name": "NFTEA.DAMAGE", "id": "1.3.6102"},
    {"name": "NFTEA.DESIGN", "id": "1.3.6101"},
    {"name": "NFTEA.DEV", "id": "1.3.6100"},
    {"name": "NFTEA.DIRECTION", "id": "1.3.6099"},
    {"name": "NFTEA.FIRE", "id": "1.3.6098"},
    {"name": "NFTEA.DETAIL", "id": "1.3.6092"},
    {"name": "NFTEA.DEATH", "id": "1.3.6091"},
    {"name": "NFTEA.AGREEMENT", "id": "1.3.6090"},
    {"name": "NFTEA.AIR", "id": "1.3.6089"},
    {"name": "NFTEA.AMOUNT", "id": "1.3.6088"},
    {"name": "NFTEA.APPROVAL", "id": "1.3.6087"},
    {"name": "NFTEA.ART", "id": "1.3.6086"},
    {"name": "NFTEA.ATTACKA", "id": "1.3.6085"},
    {"name": "NFTEA.ATTACKB", "id": "1.3.6084"},
    {"name": "NFTEA.ATTENTION", "id": "1.3.6083"},
    {"name": "NFTEA.ATTRACTION", "id": "1.3.6082"},
    {"name": "NFTEA.BALANCE", "id": "1.3.6081"},
    {"name": "NFTEA.BELIEF", "id": "1.3.6080"},
    {"name": "NFTEA.BIT", "id": "1.3.6079"},
    {"name": "NFTEA.BLOW", "id": "1.3.6078"},
    {"name": "NFTEA.HOME", "id": "1.3.6077"},
    {"name": "NFTEA.BURST", "id": "1.3.6076"},
    {"name": "NFTEA.CARE", "id": "1.3.6075"},
    {"name": "NFTEA.CAUSE", "id": "1.3.6074"},
    {"name": "NFTEA.COLOUR", "id": "1.3.6073"},
    {"name": "NFTEA.COMPARISON", "id": "1.3.6072"},
    {"name": "NFTEA.COMFORT", "id": "1.3.6071"},
    {"name": "NFTEA.COMPETE", "id": "1.3.6070"},
    {"name": "NFTEA.CONNECTION", "id": "1.3.6069"},
    {"name": "NFTEA.COPY", "id": "1.3.6068"},
    {"name": "NFTEA.CRACK", "id": "1.3.6067"},
    {"name": "NFTEA.CREDIT", "id": "1.3.6066"},
    {"name": "NFTEA.CRUSH", "id": "1.3.6065"},
    {"name": "NFTEA.DAY", "id": "1.3.6064"},
    {"name": "NFTEA.DISCOVERY", "id": "1.3.6063"},
    {"name": "ARTCASA.DCOHRNCE", "id": "1.3.6056"},
    {"name": "ARTCASA.COHRNCE", "id": "1.3.6055"},
    {"name": "ARTCASA.ICECANDL", "id": "1.3.6014"},
    {"name": "ARTCASA.TERMDART", "id": "1.3.6113"},
    {"name": "NFTEA.F3", "id": "1.3.6027"}
  ]
}
